__init__.py
cloudicorn_opentofu.py
cloudicorn_opentofu-0.10.dist-info/METADATA
cloudicorn_opentofu-0.10.dist-info/WHEEL
cloudicorn_opentofu-0.10.dist-info/top_level.txt
cloudicorn_opentofu-0.10.dist-info/RECORD
