Metadata-Version: 2.1
Name: cloudicorn-opentofu
Version: 0.10
Summary: Replaces terraform backend with opentofu
Home-page: https://github.com/jumidev/cloudicorn-cli
Author: krezreb
Author-email: josephbeeson@gmail.com
License: MIT
Requires-Dist: cloudicorn-cli
